[
  {
    "id": "4cad94c5",
    "symbol": "BLUAI",
    "direction": "long",
    "entry_price": 0.005873,
    "exit_price": 0.005798,
    "tp_price": 0.006343,
    "sl_price": 0.005798,
    "position_value": 1500.0,
    "pnl_pct": -1.28,
    "pnl_value": -19.16,
    "result": "loss",
    "reason": "sl_hit",
    "signal_score": 82,
    "ml_confidence": 56.5,
    "ai_verdict": "Score:82 ML:5650%",
    "mtf_alignment": 0,
    "open_time": "2026-02-14 11:24:57",
    "close_time": "2026-02-14 11:51:22",
    "hold_hours": 0.4,
    "strategy_type": "trend",
    "strategy": "trend_following",
    "regime": "volatile"
  },
  {
    "id": "b7b7de7d",
    "symbol": "POWER",
    "direction": "long",
    "entry_price": 0.288,
    "exit_price": 0.282,
    "tp_price": 0.31104,
    "sl_price": 0.283591,
    "position_value": 1499.71,
    "pnl_pct": -2.08,
    "pnl_value": -31.24,
    "result": "loss",
    "reason": "sl_hit",
    "signal_score": 83,
    "ml_confidence": 60.9,
    "ai_verdict": "Score:83 ML:6090%",
    "mtf_alignment": 0,
    "open_time": "2026-02-14 12:17:51",
    "close_time": "2026-02-14 12:29:02",
    "hold_hours": 0.2,
    "strategy_type": "trend",
    "strategy": "trend_following",
    "regime": "volatile"
  },
  {
    "id": "ebfed676",
    "symbol": "BLUAI",
    "direction": "long",
    "entry_price": 0.005808,
    "exit_price": 0.005713,
    "tp_price": 0.006273,
    "sl_price": 0.005719,
    "position_value": 100,
    "pnl_pct": -1.64,
    "pnl_value": -1.64,
    "result": "loss",
    "reason": "sl_hit",
    "signal_score": 85,
    "ml_confidence": 55.8,
    "ai_verdict": "AutoTrade Score:85 ML:5580%",
    "mtf_alignment": 0,
    "open_time": "2026-02-14 17:52:12",
    "close_time": "2026-02-14 18:31:36",
    "hold_hours": 0.7,
    "strategy_type": "trend",
    "strategy": "trend_following",
    "regime": "volatile"
  },
  {
    "id": "f29a4914",
    "symbol": "USD1",
    "direction": "long",
    "entry_price": 1.0,
    "exit_price": 1.0,
    "tp_price": 1.000916,
    "sl_price": 0.999825,
    "position_value": 100,
    "pnl_pct": 0.0,
    "pnl_value": 0.0,
    "result": "breakeven",
    "reason": "manual_close",
    "signal_score": 74,
    "ml_confidence": 74.7,
    "ai_verdict": "Auto 做多 Score:74 ML:75%",
    "mtf_alignment": 0,
    "open_time": "2026-02-15 00:16:57",
    "close_time": "2026-02-15 01:03:26",
    "hold_hours": 0.8,
    "strategy_type": "trend",
    "strategy": "trend_following",
    "regime": "mixed"
  },
  {
    "id": "554ece32",
    "symbol": "XAUT",
    "direction": "long",
    "entry_price": 4998.4,
    "exit_price": 4997.0,
    "tp_price": 5186.257144,
    "sl_price": 4962.448839,
    "position_value": 374.8,
    "pnl_pct": -0.03,
    "pnl_value": -0.1,
    "result": "loss",
    "reason": "manual_close",
    "signal_score": 83,
    "ml_confidence": 75.3,
    "ai_verdict": "Score:83 ML:7530%",
    "mtf_alignment": 0,
    "open_time": "2026-02-14 22:22:01",
    "close_time": "2026-02-15 01:03:29",
    "hold_hours": 2.7,
    "strategy_type": "trend",
    "strategy": "trend_following",
    "regime": "mixed"
  },
  {
    "id": "aab96f85",
    "symbol": "PIPPIN",
    "direction": "long",
    "entry_price": 0.67477,
    "exit_price": 0.69888,
    "tp_price": 0.905026,
    "sl_price": 0.630705,
    "position_value": 100,
    "pnl_pct": 3.57,
    "pnl_value": 3.57,
    "result": "win",
    "reason": "manual_close",
    "signal_score": 72,
    "ml_confidence": 41.5,
    "ai_verdict": "Auto 做多 Score:72 ML:42%",
    "mtf_alignment": 0,
    "open_time": "2026-02-15 00:16:57",
    "close_time": "2026-02-15 01:03:30",
    "hold_hours": 0.8,
    "strategy_type": "trend",
    "strategy": "trend_following",
    "regime": "mixed"
  },
  {
    "id": "3bfa6423",
    "symbol": "PAXG",
    "direction": "long",
    "entry_price": 5028.87,
    "exit_price": 5028.56,
    "tp_price": 5431.1796,
    "sl_price": 4951.878,
    "position_value": 127.11,
    "pnl_pct": -0.01,
    "pnl_value": -0.01,
    "result": "loss",
    "reason": "manual_close",
    "signal_score": 94,
    "ml_confidence": 81.1,
    "ai_verdict": "AutoTrade Score:94 ML:8110%",
    "mtf_alignment": 0,
    "open_time": "2026-02-14 18:01:12",
    "close_time": "2026-02-15 01:03:34",
    "hold_hours": 7.0,
    "strategy_type": "trend",
    "strategy": "trend_following",
    "regime": "trending"
  },
  {
    "id": "0c15cb58",
    "symbol": "XAUT",
    "direction": "long",
    "entry_price": 4999.5,
    "exit_price": 4997.0,
    "tp_price": 5399.46,
    "sl_price": 4922.957655,
    "position_value": 100,
    "pnl_pct": -0.05,
    "pnl_value": -0.05,
    "result": "loss",
    "reason": "manual_close",
    "signal_score": 94,
    "ml_confidence": 81.1,
    "ai_verdict": "AutoTrade Score:94 ML:8110%",
    "mtf_alignment": 0,
    "open_time": "2026-02-14 17:52:12",
    "close_time": "2026-02-15 01:03:34",
    "hold_hours": 7.2,
    "strategy_type": "trend",
    "strategy": "trend_following",
    "regime": "trending"
  },
  {
    "id": "899961a2",
    "symbol": "COINON",
    "direction": "short",
    "entry_price": 165.88,
    "exit_price": 166.84,
    "tp_price": 142.354284,
    "sl_price": 170.382234,
    "position_value": 211.42,
    "pnl_pct": -0.58,
    "pnl_value": -1.22,
    "result": "loss",
    "reason": "manual_close",
    "signal_score": 70,
    "ml_confidence": 63.5,
    "ai_verdict": "Score:70 ML:6350%",
    "mtf_alignment": 0,
    "open_time": "2026-02-14 21:48:36",
    "close_time": "2026-02-15 01:03:40",
    "hold_hours": 3.3,
    "strategy_type": "trend",
    "strategy": "trend_following",
    "regime": "mixed"
  },
  {
    "id": "a5d13b13",
    "symbol": "GPUAI",
    "direction": "long",
    "entry_price": 0.027862,
    "exit_price": 0.023705,
    "tp_price": 0.048778,
    "sl_price": 0.023859,
    "position_value": 100,
    "pnl_pct": -14.92,
    "pnl_value": -14.92,
    "result": "loss",
    "reason": "sl_hit",
    "signal_score": 67,
    "ml_confidence": 52.9,
    "ai_verdict": "Auto 做多 Score:67 ML:53%",
    "mtf_alignment": 0,
    "open_time": "2026-02-15 01:08:02",
    "close_time": "2026-02-15 03:04:05",
    "hold_hours": 1.9,
    "strategy_type": "trend",
    "strategy": "trend_following",
    "regime": "ranging"
  },
  {
    "id": "582f3644-partial",
    "symbol": "ZEC",
    "direction": "long",
    "entry_price": 285.9,
    "exit_price": 313.04,
    "tp_price": 330.114284,
    "sl_price": 302.00321449999996,
    "position_value": 50.0,
    "pnl_pct": 9.49,
    "pnl_value": 4.75,
    "result": "win",
    "reason": "partial_tp",
    "signal_score": 64,
    "ml_confidence": 50.8,
    "ai_verdict": "Auto 做多 Score:64 ML:51%",
    "mtf_alignment": 0,
    "open_time": "2026-02-15 01:05:17",
    "close_time": "2026-02-15 03:48:08",
    "hold_hours": 2.7,
    "strategy_type": "trend",
    "strategy": "trend_following",
    "regime": "ranging"
  },
  {
    "id": "582f3644",
    "symbol": "ZEC",
    "direction": "long",
    "entry_price": 285.9,
    "exit_price": 312.6,
    "tp_price": 330.114284,
    "sl_price": 312.9732145,
    "position_value": 100,
    "pnl_pct": 9.34,
    "pnl_value": 4.67,
    "result": "win",
    "reason": "sl_hit",
    "signal_score": 64,
    "ml_confidence": 50.8,
    "ai_verdict": "Auto 做多 Score:64 ML:51%",
    "mtf_alignment": 0,
    "open_time": "2026-02-15 01:05:17",
    "close_time": "2026-02-15 04:03:02",
    "hold_hours": 3.0,
    "strategy_type": "trend",
    "strategy": "trend_following",
    "regime": "ranging"
  },
  {
    "id": "db84a07a",
    "symbol": "FF",
    "direction": "long",
    "entry_price": 0.08118,
    "exit_price": 0.08295,
    "tp_price": 0.087976,
    "sl_price": 0.0829905,
    "position_value": 100,
    "pnl_pct": 2.18,
    "pnl_value": 2.18,
    "result": "win",
    "reason": "sl_hit",
    "signal_score": 69,
    "ml_confidence": 75.4,
    "ai_verdict": "Auto 做多 Score:69 ML:75%",
    "mtf_alignment": 0,
    "open_time": "2026-02-15 03:06:19",
    "close_time": "2026-02-15 05:32:10",
    "hold_hours": 2.4,
    "strategy_type": "trend",
    "strategy": "trend_following",
    "regime": "ranging"
  },
  {
    "id": "7f1129ac",
    "symbol": "MON",
    "direction": "long",
    "entry_price": 0.02453,
    "exit_price": 0.02358,
    "tp_price": 0.029482,
    "sl_price": 0.023582,
    "position_value": 100,
    "pnl_pct": -3.87,
    "pnl_value": -3.87,
    "result": "loss",
    "reason": "sl_hit",
    "signal_score": 71,
    "ml_confidence": 46.5,
    "ai_verdict": "Auto 做多 Score:71 ML:46%",
    "mtf_alignment": 0,
    "open_time": "2026-02-15 01:05:17",
    "close_time": "2026-02-15 07:20:59",
    "hold_hours": 6.3,
    "strategy_type": "trend",
    "strategy": "trend_following",
    "regime": "trending"
  },
  {
    "id": "f981200e",
    "symbol": "POWER",
    "direction": "long",
    "entry_price": 0.2767,
    "exit_price": 0.24,
    "tp_price": 0.459044,
    "sl_price": 0.241804,
    "position_value": 100,
    "pnl_pct": -13.26,
    "pnl_value": -13.26,
    "result": "loss",
    "reason": "sl_hit",
    "signal_score": 69,
    "ml_confidence": 64.9,
    "ai_verdict": "Auto 做多 Score:69 ML:65%",
    "mtf_alignment": 0,
    "open_time": "2026-02-15 01:08:02",
    "close_time": "2026-02-15 08:50:08",
    "hold_hours": 7.7,
    "strategy_type": "trend",
    "strategy": "trend_following",
    "regime": "ranging"
  },
  {
    "id": "43160c2e",
    "symbol": "ASTER",
    "direction": "long",
    "entry_price": 0.7358,
    "exit_price": 0.7178,
    "tp_price": 0.821716,
    "sl_price": 0.719358,
    "position_value": 100,
    "pnl_pct": -2.45,
    "pnl_value": -2.45,
    "result": "loss",
    "reason": "sl_hit",
    "signal_score": 67,
    "ml_confidence": 58.7,
    "ai_verdict": "Auto 做多 Score:67 ML:59%",
    "mtf_alignment": 0,
    "open_time": "2026-02-15 07:23:09",
    "close_time": "2026-02-15 09:29:33",
    "hold_hours": 2.1,
    "strategy_type": "trend",
    "strategy": "trend_following",
    "regime": "ranging"
  },
  {
    "id": "dd27b1d7",
    "symbol": "FF",
    "direction": "long",
    "entry_price": 0.08196,
    "exit_price": 0.08318,
    "tp_price": 0.089244,
    "sl_price": 0.0831895,
    "position_value": 100,
    "pnl_pct": 1.49,
    "pnl_value": 1.49,
    "result": "win",
    "reason": "sl_hit",
    "signal_score": 70,
    "ml_confidence": 77.5,
    "ai_verdict": "Auto 做多 Score:70 ML:78%",
    "mtf_alignment": 0,
    "open_time": "2026-02-15 07:23:09",
    "close_time": "2026-02-15 09:31:48",
    "hold_hours": 2.1,
    "strategy_type": "trend",
    "strategy": "trend_following",
    "regime": "mixed"
  },
  {
    "id": "ec3c22df",
    "symbol": "BEAT",
    "direction": "long",
    "entry_price": 0.3123,
    "exit_price": 0.2931,
    "tp_price": 0.3941,
    "sl_price": 0.296646,
    "position_value": 100,
    "pnl_pct": -6.15,
    "pnl_value": -6.15,
    "result": "loss",
    "reason": "sl_hit",
    "signal_score": 74,
    "ml_confidence": 53.6,
    "ai_verdict": "Auto 做多 Score:74 ML:54%",
    "mtf_alignment": 0,
    "open_time": "2026-02-15 09:34:05",
    "close_time": "2026-02-15 09:43:47",
    "hold_hours": 0.2,
    "strategy_type": "trend",
    "strategy": "trend_following",
    "regime": "mixed"
  },
  {
    "id": "7233f683",
    "symbol": "BCH",
    "direction": "long",
    "entry_price": 565.99,
    "exit_price": 556.3,
    "tp_price": 614.687144,
    "sl_price": 556.670584,
    "position_value": 100,
    "pnl_pct": -1.71,
    "pnl_value": -1.71,
    "result": "loss",
    "reason": "sl_hit",
    "signal_score": 68,
    "ml_confidence": 60.6,
    "ai_verdict": "Auto 做多 Score:68 ML:61%",
    "mtf_alignment": 0,
    "open_time": "2026-02-15 03:06:19",
    "close_time": "2026-02-15 16:33:53",
    "hold_hours": 13.5,
    "strategy_type": "trend",
    "strategy": "trend_following",
    "regime": "ranging"
  },
  {
    "id": "1f7ef2c0",
    "symbol": "HYPE",
    "direction": "long",
    "entry_price": 31.698,
    "exit_price": 30.87,
    "tp_price": 35.705716,
    "sl_price": 30.931023,
    "position_value": 100,
    "pnl_pct": -2.61,
    "pnl_value": -2.61,
    "result": "loss",
    "reason": "sl_hit",
    "signal_score": 67,
    "ml_confidence": 64.2,
    "ai_verdict": "Auto 做多 Score:67 ML:64%",
    "mtf_alignment": 0,
    "open_time": "2026-02-15 07:23:09",
    "close_time": "2026-02-15 16:33:53",
    "hold_hours": 9.2,
    "strategy_type": "trend",
    "strategy": "trend_following",
    "regime": "ranging"
  },
  {
    "id": "3e80793c",
    "symbol": "COAI",
    "direction": "long",
    "entry_price": 0.4217,
    "exit_price": 0.3767,
    "tp_price": 0.5507,
    "sl_price": 0.397013,
    "position_value": 100,
    "pnl_pct": -10.67,
    "pnl_value": -10.67,
    "result": "loss",
    "reason": "over_limit_cleanup",
    "signal_score": 69,
    "ml_confidence": 73.7,
    "ai_verdict": "Auto 做多 Score:69 ML:74%",
    "mtf_alignment": 0,
    "strategy_type": "trend",
    "open_time": "2026-02-15 01:08:02",
    "close_time": "2026-02-15 17:48:07",
    "hold_hours": 16.7,
    "strategy": "trend_following",
    "regime": "ranging"
  },
  {
    "id": "2d6f8426",
    "symbol": "OM",
    "direction": "long",
    "entry_price": 0.06584,
    "exit_price": 0.06283,
    "tp_price": 0.092344,
    "sl_price": 0.060768,
    "position_value": 100,
    "pnl_pct": -4.57,
    "pnl_value": -4.57,
    "result": "loss",
    "reason": "over_limit_cleanup",
    "signal_score": 74,
    "ml_confidence": 55.4,
    "ai_verdict": "Auto 做多 Score:74 ML:55%",
    "mtf_alignment": 0,
    "strategy_type": "trend",
    "open_time": "2026-02-15 09:34:07",
    "close_time": "2026-02-15 17:48:07",
    "hold_hours": 8.2,
    "strategy": "trend_following",
    "regime": "trending"
  },
  {
    "id": "7f37890b",
    "symbol": "PYTH",
    "direction": "long",
    "entry_price": 0.05721,
    "exit_price": 0.05699,
    "tp_price": 0.06699,
    "sl_price": 0.055338,
    "position_value": 100,
    "pnl_pct": -0.38,
    "pnl_value": -0.38,
    "result": "loss",
    "reason": "over_limit_cleanup",
    "signal_score": 68,
    "ml_confidence": 56.8,
    "ai_verdict": "Auto 做多 Score:68 ML:57%",
    "mtf_alignment": 0,
    "strategy_type": "trend",
    "open_time": "2026-02-15 09:34:05",
    "close_time": "2026-02-15 17:48:07",
    "hold_hours": 8.2,
    "strategy": "trend_following",
    "regime": "ranging"
  },
  {
    "id": "37cc4bc7",
    "symbol": "XPL",
    "direction": "long",
    "entry_price": 0.10136,
    "exit_price": 0.10107,
    "tp_price": 0.116308,
    "sl_price": 0.098195,
    "position_value": 499.57,
    "pnl_pct": -0.29,
    "pnl_value": -1.43,
    "result": "loss",
    "reason": "over_limit_cleanup",
    "signal_score": 69,
    "ml_confidence": 49.1,
    "ai_verdict": "Auto 做多 Score:69 ML:49%",
    "mtf_alignment": 0,
    "strategy_type": "trend",
    "open_time": "2026-02-15 16:37:29",
    "close_time": "2026-02-15 17:48:07",
    "hold_hours": 1.2,
    "strategy": "trend_following",
    "regime": "ranging"
  },
  {
    "id": "f797c6d0",
    "symbol": "USELESS",
    "direction": "long",
    "entry_price": 0.04427,
    "exit_price": 0.04538,
    "tp_price": 0.056026,
    "sl_price": 0.047670500000000005,
    "position_value": 499.57,
    "pnl_pct": 2.51,
    "pnl_value": 12.53,
    "result": "win",
    "reason": "sl_hit",
    "signal_score": 70,
    "ml_confidence": 42.3,
    "ai_verdict": "Auto 做多 Score:70 ML:42%",
    "mtf_alignment": 0,
    "strategy_type": "trend",
    "open_time": "2026-02-15 16:37:29",
    "close_time": "2026-02-15 20:27:39",
    "hold_hours": 3.8,
    "strategy": "trend_following",
    "regime": "mixed"
  },
  {
    "id": "d791d077",
    "symbol": "STABLE",
    "direction": "long",
    "entry_price": 0.023767,
    "exit_price": 0.023446,
    "tp_price": 0.027959,
    "sl_price": 0.0234526,
    "position_value": 499.66,
    "pnl_pct": -1.35,
    "pnl_value": -6.75,
    "result": "loss",
    "reason": "sl_hit",
    "signal_score": 83,
    "ml_confidence": 66.8,
    "ai_verdict": "Auto 做多 Score:83 ML:67%",
    "mtf_alignment": 0,
    "strategy_type": "trend",
    "open_time": "2026-02-15 21:33:32",
    "close_time": "2026-02-15 21:52:05",
    "hold_hours": 0.3,
    "strategy": "trend_following",
    "regime": "volatile"
  },
  {
    "id": "391e3711",
    "symbol": "我踏马来了",
    "direction": "long",
    "entry_price": 0.026464,
    "exit_price": 0.025684,
    "tp_price": 0.035404,
    "sl_price": 0.0257935,
    "position_value": 100,
    "pnl_pct": -2.95,
    "pnl_value": -2.95,
    "result": "loss",
    "reason": "sl_hit",
    "signal_score": 72,
    "ml_confidence": 47.3,
    "ai_verdict": "Auto 做多 Score:72 ML:47%",
    "mtf_alignment": 0,
    "strategy_type": "trend",
    "open_time": "2026-02-15 00:42:31",
    "close_time": "2026-02-15 21:54:49",
    "hold_hours": 21.2,
    "strategy": "trend_following",
    "regime": "trending"
  },
  {
    "id": "1be549f3",
    "symbol": "ZAMA",
    "direction": "long",
    "entry_price": 0.02095,
    "exit_price": 0.0205,
    "tp_price": 0.026506,
    "sl_price": 0.0205333,
    "position_value": 100,
    "pnl_pct": -2.15,
    "pnl_value": -2.15,
    "result": "loss",
    "reason": "sl_hit",
    "signal_score": 74,
    "ml_confidence": 57.8,
    "ai_verdict": "Auto 做多 Score:74 ML:58%",
    "mtf_alignment": 0,
    "strategy_type": "trend",
    "open_time": "2026-02-15 03:06:19",
    "close_time": "2026-02-15 21:54:49",
    "hold_hours": 18.8,
    "strategy": "trend_following",
    "regime": "trending"
  },
  {
    "id": "b1222ec0",
    "symbol": "H",
    "direction": "long",
    "entry_price": 0.22102,
    "exit_price": 0.23628,
    "tp_price": 0.300092,
    "sl_price": 0.21651199999999998,
    "position_value": 499.57,
    "pnl_pct": 6.9,
    "pnl_value": 34.49,
    "result": "win",
    "reason": "manual_close",
    "signal_score": 69,
    "ml_confidence": 49.9,
    "ai_verdict": "Auto 做多 Score:69 ML:50%",
    "mtf_alignment": 0,
    "strategy_type": "trend",
    "open_time": "2026-02-15 16:37:29",
    "close_time": "2026-02-15 23:07:13",
    "hold_hours": 6.5,
    "strategy": "trend_following",
    "regime": "ranging"
  },
  {
    "id": "72655450",
    "symbol": "KITE",
    "direction": "long",
    "entry_price": 0.22189,
    "exit_price": 0.21511,
    "tp_price": 0.288106,
    "sl_price": 0.2169238,
    "position_value": 499.66,
    "pnl_pct": -3.06,
    "pnl_value": -15.27,
    "result": "loss",
    "reason": "sl_hit",
    "signal_score": 86,
    "ml_confidence": 48.1,
    "ai_verdict": "Auto 做多 Score:86 ML:48%",
    "mtf_alignment": 0,
    "strategy_type": "trend",
    "open_time": "2026-02-15 21:43:46",
    "close_time": "2026-02-16 06:37:56",
    "hold_hours": 8.9,
    "strategy": "trend_following",
    "regime": "trending"
  },
  {
    "id": "db240fcb",
    "symbol": "XAUT",
    "direction": "long",
    "entry_price": 4998.4,
    "exit_price": 4970.5,
    "tp_price": 5148.789791180055,
    "sl_price": 4984.3107142,
    "position_value": 374.8,
    "pnl_pct": -0.56,
    "pnl_value": -2.09,
    "result": "loss",
    "reason": "sl_hit",
    "signal_score": 83,
    "ml_confidence": 75.3,
    "ai_verdict": "Score:83 ML:7530%",
    "mtf_alignment": 0,
    "strategy_type": "range",
    "open_time": "2026-02-14 22:20:07",
    "close_time": "2026-02-16 10:56:39",
    "hold_hours": 36.6,
    "strategy": "range_harvester",
    "regime": "trending"
  },
  {
    "id": "1a8f1372",
    "symbol": "PIPPIN",
    "direction": "long",
    "entry_price": 0.69272,
    "exit_price": 0.68255,
    "tp_price": 0.933068,
    "sl_price": 0.686313,
    "position_value": 100,
    "pnl_pct": -1.47,
    "pnl_value": -1.47,
    "result": "loss",
    "reason": "sl_hit",
    "signal_score": 72,
    "ml_confidence": 41.5,
    "ai_verdict": "Auto 做多 Score:72 ML:42%",
    "mtf_alignment": 0,
    "strategy_type": "trend",
    "open_time": "2026-02-15 01:05:17",
    "close_time": "2026-02-16 10:56:39",
    "hold_hours": 33.9,
    "strategy": "trend_following",
    "regime": "trending"
  },
  {
    "id": "0f4c4450-partial-s1",
    "symbol": "STABLE",
    "direction": "long",
    "entry_price": 0.023535,
    "exit_price": 0.026945,
    "tp_price": 0.027787,
    "sl_price": 0.02186927,
    "position_value": 149.88,
    "pnl_pct": 14.49,
    "pnl_value": 21.72,
    "result": "win",
    "reason": "partial_tp_s1",
    "signal_score": 80,
    "ml_confidence": 63.8,
    "ai_verdict": "Auto 做多 Score:80 ML:64%",
    "mtf_alignment": 0,
    "strategy_type": "trend",
    "open_time": "2026-02-15 22:07:31",
    "close_time": "2026-02-16 13:51:57",
    "hold_hours": 15.7,
    "strategy": "trend_following",
    "regime": "trending"
  },
  {
    "id": "0f4c4450-partial-s2",
    "symbol": "STABLE",
    "direction": "long",
    "entry_price": 0.023535,
    "exit_price": 0.026945,
    "tp_price": 0.027787,
    "sl_price": 0.02186927,
    "position_value": 104.91,
    "pnl_pct": 14.49,
    "pnl_value": 15.2,
    "result": "win",
    "reason": "partial_tp_s2",
    "signal_score": 80,
    "ml_confidence": 63.8,
    "ai_verdict": "Auto 做多 Score:80 ML:64%",
    "mtf_alignment": 0,
    "strategy_type": "trend",
    "open_time": "2026-02-15 22:07:31",
    "close_time": "2026-02-16 13:51:57",
    "hold_hours": 15.7,
    "strategy": "trend_following",
    "regime": "trending"
  },
  {
    "id": "0f4c4450",
    "symbol": "STABLE",
    "direction": "long",
    "entry_price": 0.023535,
    "exit_price": 0.027858,
    "tp_price": 0.027787,
    "sl_price": 0.0273265,
    "position_value": 499.59,
    "pnl_pct": 18.37,
    "pnl_value": 44.97,
    "result": "win",
    "reason": "tp_hit",
    "signal_score": 80,
    "ml_confidence": 63.8,
    "ai_verdict": "Auto 做多 Score:80 ML:64%",
    "mtf_alignment": 0,
    "strategy_type": "trend",
    "open_time": "2026-02-15 22:07:31",
    "close_time": "2026-02-16 14:34:17",
    "hold_hours": 16.4,
    "strategy": "trend_following",
    "regime": "trending"
  },
  {
    "id": "dc3687ec",
    "symbol": "AAVE",
    "direction": "short",
    "entry_price": 129.17,
    "exit_price": 127.92,
    "tp_price": 116.21,
    "sl_price": 127.64,
    "position_value": 499.51,
    "pnl_pct": 0.97,
    "pnl_value": 4.83,
    "result": "win",
    "reason": "sl_hit",
    "signal_score": 70,
    "ml_confidence": 56.8,
    "ai_verdict": "Score:70 ML:57%",
    "mtf_alignment": 0,
    "strategy_type": "trend",
    "open_time": "2026-02-15 20:26:21",
    "close_time": "2026-02-16 17:12:30",
    "hold_hours": 20.8,
    "strategy": "trend_following",
    "regime": "trending"
  },
  {
    "id": "a578fcfd",
    "symbol": "AVAX",
    "direction": "long",
    "entry_price": 9.327,
    "exit_price": 9.268,
    "tp_price": 10.020428,
    "sl_price": 9.274992899999999,
    "position_value": 500.08,
    "pnl_pct": -0.63,
    "pnl_value": -3.16,
    "result": "loss",
    "reason": "sl_hit",
    "signal_score": 69,
    "ml_confidence": 61.2,
    "ai_verdict": "Auto 做多 Score:69 ML:61%",
    "mtf_alignment": 0,
    "strategy_type": "trend",
    "open_time": "2026-02-16 17:38:05",
    "close_time": "2026-02-16 18:28:05",
    "hold_hours": 0.8,
    "strategy": "trend_following",
    "regime": "ranging"
  },
  {
    "id": "84e73e23",
    "symbol": "HNT",
    "direction": "long",
    "entry_price": 1.4347,
    "exit_price": 1.4031,
    "tp_price": 1.824272,
    "sl_price": 1.4054821000000002,
    "position_value": 500.06,
    "pnl_pct": -2.2,
    "pnl_value": -11.01,
    "result": "loss",
    "reason": "sl_hit",
    "signal_score": 83,
    "ml_confidence": 49.6,
    "ai_verdict": "Auto 做多 Score:83 ML:50%",
    "mtf_alignment": 0,
    "strategy_type": "trend",
    "open_time": "2026-02-16 18:34:21",
    "close_time": "2026-02-16 19:17:33",
    "hold_hours": 0.7,
    "strategy": "trend_following",
    "regime": "volatile"
  },
  {
    "id": "08acc0b7",
    "symbol": "AR",
    "direction": "long",
    "entry_price": 2.029,
    "exit_price": 2.006,
    "tp_price": 2.243572,
    "sl_price": 2.0129071,
    "position_value": 500.02,
    "pnl_pct": -1.13,
    "pnl_value": -5.67,
    "result": "loss",
    "reason": "sl_hit",
    "signal_score": 60,
    "ml_confidence": 46.7,
    "ai_verdict": "Auto 做多 Score:60 ML:47%",
    "mtf_alignment": 0,
    "strategy_type": "trend",
    "open_time": "2026-02-16 17:18:17",
    "close_time": "2026-02-16 19:20:42",
    "hold_hours": 2.0,
    "strategy": "trend_following",
    "regime": "ranging"
  },
  {
    "id": "2628aa87",
    "symbol": "JASMY",
    "direction": "long",
    "entry_price": 0.006003,
    "exit_price": 0.005963,
    "tp_price": 0.006507,
    "sl_price": 0.0059651999999999995,
    "position_value": 500.02,
    "pnl_pct": -0.67,
    "pnl_value": -3.33,
    "result": "loss",
    "reason": "sl_hit",
    "signal_score": 68,
    "ml_confidence": 46.4,
    "ai_verdict": "Auto 做多 Score:68 ML:46%",
    "mtf_alignment": 0,
    "strategy_type": "trend",
    "open_time": "2026-02-16 17:21:56",
    "close_time": "2026-02-16 19:20:42",
    "hold_hours": 2.0,
    "strategy": "trend_following",
    "regime": "ranging"
  },
  {
    "id": "91a04b6b",
    "symbol": "IMX",
    "direction": "long",
    "entry_price": 0.1668,
    "exit_price": 0.16483,
    "tp_price": 0.182564,
    "sl_price": 0.1656177,
    "position_value": 500.03,
    "pnl_pct": -1.18,
    "pnl_value": -5.91,
    "result": "loss",
    "reason": "sl_hit",
    "signal_score": 70,
    "ml_confidence": 47.2,
    "ai_verdict": "Auto 做多 Score:70 ML:47%",
    "mtf_alignment": 0,
    "strategy_type": "trend",
    "open_time": "2026-02-16 17:28:21",
    "close_time": "2026-02-16 19:20:42",
    "hold_hours": 1.9,
    "strategy": "trend_following",
    "regime": "mixed"
  },
  {
    "id": "2e423a93",
    "symbol": "CRV",
    "direction": "long",
    "entry_price": 0.2543,
    "exit_price": 0.2522,
    "tp_price": 0.278872,
    "sl_price": 0.25245710000000005,
    "position_value": 500.02,
    "pnl_pct": -0.83,
    "pnl_value": -4.13,
    "result": "loss",
    "reason": "sl_hit",
    "signal_score": 69,
    "ml_confidence": 53.5,
    "ai_verdict": "Auto 做多 Score:69 ML:54%",
    "mtf_alignment": 0,
    "strategy_type": "trend",
    "open_time": "2026-02-16 17:21:56",
    "close_time": "2026-02-16 19:23:35",
    "hold_hours": 2.0,
    "strategy": "trend_following",
    "regime": "ranging"
  },
  {
    "id": "b76657f8",
    "symbol": "FIL",
    "direction": "long",
    "entry_price": 0.9679,
    "exit_price": 0.9544,
    "tp_price": 1.060156,
    "sl_price": 0.9609808,
    "position_value": 500.04,
    "pnl_pct": -1.39,
    "pnl_value": -6.97,
    "result": "loss",
    "reason": "sl_hit",
    "signal_score": 70,
    "ml_confidence": 46.4,
    "ai_verdict": "Auto 做多 Score:70 ML:46%",
    "mtf_alignment": 0,
    "strategy_type": "trend",
    "open_time": "2026-02-16 17:31:56",
    "close_time": "2026-02-16 19:23:35",
    "hold_hours": 1.9,
    "strategy": "trend_following",
    "regime": "mixed"
  },
  {
    "id": "87860389-partial-s1",
    "symbol": "ATOM",
    "direction": "long",
    "entry_price": 2.143,
    "exit_price": 2.231,
    "tp_price": 2.303856,
    "sl_price": 2.151786,
    "position_value": 150.01,
    "pnl_pct": 4.11,
    "pnl_value": 6.16,
    "result": "win",
    "reason": "partial_tp_s1",
    "signal_score": 70,
    "ml_confidence": 48.6,
    "ai_verdict": "Auto 做多 Score:70 ML:49%",
    "mtf_alignment": 0,
    "strategy_type": "trend",
    "open_time": "2026-02-16 17:18:17",
    "close_time": "2026-02-16 21:23:54",
    "hold_hours": 4.1,
    "strategy": "trend_following",
    "regime": "mixed"
  },
  {
    "id": "87860389",
    "symbol": "ATOM",
    "direction": "long",
    "entry_price": 2.143,
    "exit_price": 2.193,
    "tp_price": 2.303856,
    "sl_price": 2.2028502,
    "position_value": 500.02,
    "pnl_pct": 2.33,
    "pnl_value": 8.17,
    "result": "win",
    "reason": "sl_hit",
    "signal_score": 70,
    "ml_confidence": 48.6,
    "ai_verdict": "Auto 做多 Score:70 ML:49%",
    "mtf_alignment": 0,
    "strategy_type": "trend",
    "open_time": "2026-02-16 17:18:17",
    "close_time": "2026-02-16 21:57:19",
    "hold_hours": 4.7,
    "strategy": "trend_following",
    "regime": "mixed"
  },
  {
    "id": "060b7fe7",
    "symbol": "HBAR",
    "direction": "long",
    "entry_price": 0.10069,
    "exit_price": 0.09933,
    "tp_price": 0.111006,
    "sl_price": 0.0999163,
    "position_value": 500.02,
    "pnl_pct": -1.35,
    "pnl_value": -6.75,
    "result": "loss",
    "reason": "sl_hit",
    "signal_score": 70,
    "ml_confidence": 46.4,
    "ai_verdict": "Auto 做多 Score:70 ML:46%",
    "mtf_alignment": 0,
    "strategy_type": "trend",
    "open_time": "2026-02-16 17:18:17",
    "close_time": "2026-02-16 23:33:30",
    "hold_hours": 6.3,
    "strategy": "trend_following",
    "regime": "trending"
  },
  {
    "id": "e437dad2",
    "symbol": "STABLE",
    "direction": "short",
    "entry_price": 0.032126,
    "exit_price": 0.033748,
    "tp_price": 0.024366,
    "sl_price": 0.032708,
    "position_value": 424.88,
    "pnl_pct": -5.05,
    "pnl_value": -21.45,
    "result": "loss",
    "reason": "sl_hit",
    "signal_score": 76,
    "ml_confidence": 55.4,
    "ai_verdict": "Auto 做空 Score:76 ML:55% 做空评分=70",
    "mtf_alignment": 0,
    "strategy_type": "trend",
    "open_time": "2026-02-17 12:17:27",
    "close_time": "2026-02-17 13:09:24",
    "hold_hours": 0.9
  },
  {
    "id": "69a4b564-partial-s1",
    "symbol": "STABLE",
    "direction": "short",
    "entry_price": 0.033401,
    "exit_price": 0.02985,
    "tp_price": 0.025205,
    "sl_price": 0.033562,
    "position_value": 127.44,
    "pnl_pct": 10.63,
    "pnl_value": 13.55,
    "result": "win",
    "reason": "partial_tp_s1",
    "signal_score": 76,
    "ml_confidence": 54.5,
    "ai_verdict": "Auto 做空 Score:76 ML:54% 做空评分=70",
    "mtf_alignment": 0,
    "strategy_type": "trend",
    "open_time": "2026-02-17 13:14:15",
    "close_time": "2026-02-17 14:21:17",
    "hold_hours": 1.1
  },
  {
    "id": "69a4b564",
    "symbol": "STABLE",
    "direction": "short",
    "entry_price": 0.033401,
    "exit_price": 0.030783,
    "tp_price": 0.025205,
    "sl_price": 0.0306933,
    "position_value": 424.79,
    "pnl_pct": 7.84,
    "pnl_value": 23.31,
    "result": "win",
    "reason": "sl_hit",
    "signal_score": 76,
    "ml_confidence": 54.5,
    "ai_verdict": "Auto 做空 Score:76 ML:54% 做空评分=70",
    "mtf_alignment": 0,
    "strategy_type": "trend",
    "open_time": "2026-02-17 13:14:15",
    "close_time": "2026-02-17 14:50:25",
    "hold_hours": 1.6
  },
  {
    "id": "5faa0368",
    "symbol": "WLFI",
    "direction": "long",
    "entry_price": 0.122,
    "exit_price": 0.1209,
    "tp_price": 0.132748,
    "sl_price": 0.1210787,
    "position_value": 878.91,
    "pnl_pct": -0.9,
    "pnl_value": -7.92,
    "result": "loss",
    "reason": "sl_hit",
    "signal_score": 78,
    "ml_confidence": 40.0,
    "ai_verdict": "Auto 做多 Score:78 ML:40%",
    "mtf_alignment": 0,
    "strategy_type": "range",
    "open_time": "2026-02-21 21:59:19",
    "close_time": "2026-02-21 22:59:21",
    "hold_hours": 1.0
  },
  {
    "id": "96cb637b",
    "symbol": "ADA",
    "direction": "long",
    "entry_price": 0.2846,
    "exit_price": 0.2827,
    "tp_price": 0.305551,
    "sl_price": 0.2828042,
    "position_value": 881.69,
    "pnl_pct": -0.67,
    "pnl_value": -5.89,
    "result": "loss",
    "reason": "sl_hit",
    "signal_score": 75,
    "ml_confidence": 51.3,
    "ai_verdict": "Auto 做多 Score:75 ML:51%",
    "mtf_alignment": 0,
    "strategy_type": "range",
    "open_time": "2026-02-21 22:26:42",
    "close_time": "2026-02-21 23:29:15",
    "hold_hours": 1.0
  },
  {
    "id": "92b865b3",
    "symbol": "WIF",
    "direction": "long",
    "entry_price": 0.2268,
    "exit_price": 0.2252,
    "tp_price": 0.242225,
    "sl_price": 0.2254779,
    "position_value": 879.01,
    "pnl_pct": -0.71,
    "pnl_value": -6.2,
    "result": "loss",
    "reason": "sl_hit",
    "signal_score": 75,
    "ml_confidence": 54.5,
    "ai_verdict": "Auto 做多 Score:75 ML:54%",
    "mtf_alignment": 0,
    "strategy_type": "range",
    "open_time": "2026-02-21 22:21:53",
    "close_time": "2026-02-21 23:33:54",
    "hold_hours": 1.2
  },
  {
    "id": "27117476-partial-s1",
    "symbol": "POL",
    "direction": "long",
    "entry_price": 0.11155,
    "exit_price": 0.11527,
    "tp_price": 0.119789,
    "sl_price": 0.112296,
    "position_value": 266.14,
    "pnl_pct": 3.33,
    "pnl_value": 8.88,
    "result": "win",
    "reason": "partial_tp_s1",
    "signal_score": 75,
    "ml_confidence": 55.9,
    "ai_verdict": "Auto 做多 Score:75 ML:56%",
    "mtf_alignment": 0,
    "strategy_type": "grid",
    "open_time": "2026-02-21 22:16:02",
    "close_time": "2026-02-21 23:34:02",
    "hold_hours": 1.3
  },
  {
    "id": "b909c1c9",
    "symbol": "ONDO",
    "direction": "long",
    "entry_price": 0.272,
    "exit_price": 0.2702,
    "tp_price": 0.2911,
    "sl_price": 0.2703629,
    "position_value": 879.11,
    "pnl_pct": -0.66,
    "pnl_value": -5.82,
    "result": "loss",
    "reason": "sl_hit",
    "signal_score": 75,
    "ml_confidence": 59.8,
    "ai_verdict": "Auto 做多 Score:75 ML:60%",
    "mtf_alignment": 0,
    "strategy_type": "range",
    "open_time": "2026-02-21 21:59:18",
    "close_time": "2026-02-22 00:03:04",
    "hold_hours": 2.1
  },
  {
    "id": "27117476",
    "symbol": "POL",
    "direction": "long",
    "entry_price": 0.11155,
    "exit_price": 0.11367,
    "tp_price": 0.119789,
    "sl_price": 0.1136822,
    "position_value": 887.15,
    "pnl_pct": 1.9,
    "pnl_value": 11.8,
    "result": "win",
    "reason": "sl_hit",
    "signal_score": 75,
    "ml_confidence": 55.9,
    "ai_verdict": "Auto 做多 Score:75 ML:56%",
    "mtf_alignment": 0,
    "strategy_type": "grid",
    "open_time": "2026-02-21 22:16:02",
    "close_time": "2026-02-22 00:03:45",
    "hold_hours": 1.8
  },
  {
    "id": "f5888ca6",
    "symbol": "HBAR",
    "direction": "long",
    "entry_price": 0.10064,
    "exit_price": 0.09934,
    "tp_price": 0.106639,
    "sl_price": 0.10012579999999999,
    "position_value": 881.48,
    "pnl_pct": -1.29,
    "pnl_value": -11.39,
    "result": "loss",
    "reason": "sl_hit",
    "signal_score": 75,
    "ml_confidence": 50.3,
    "ai_verdict": "Auto 做多 Score:75 ML:50%",
    "mtf_alignment": 0,
    "strategy_type": "range",
    "open_time": "2026-02-21 22:04:22",
    "close_time": "2026-02-22 08:31:34",
    "hold_hours": 10.5
  },
  {
    "id": "5f6730ec-partial-s1",
    "symbol": "ARC",
    "direction": "long",
    "entry_price": 0.08047,
    "exit_price": 0.08475,
    "tp_price": 0.091015,
    "sl_price": 0.081607,
    "position_value": 195.62,
    "pnl_pct": 5.32,
    "pnl_value": 10.4,
    "result": "win",
    "reason": "partial_tp_s1",
    "signal_score": 73,
    "ml_confidence": 53.2,
    "ai_verdict": "Auto 做多 Score:73 ML:53%",
    "mtf_alignment": 0,
    "strategy_type": "trend",
    "open_time": "2026-02-22 17:12:14",
    "close_time": "2026-02-22 18:51:30",
    "hold_hours": 1.7
  },
  {
    "id": "5f6730ec-partial-s2",
    "symbol": "ARC",
    "direction": "long",
    "entry_price": 0.08047,
    "exit_price": 0.08787,
    "tp_price": 0.091015,
    "sl_price": 0.0856209,
    "position_value": 136.93,
    "pnl_pct": 9.2,
    "pnl_value": 12.59,
    "result": "win",
    "reason": "partial_tp_s2",
    "signal_score": 73,
    "ml_confidence": 53.2,
    "ai_verdict": "Auto 做多 Score:73 ML:53%",
    "mtf_alignment": 0,
    "strategy_type": "trend",
    "open_time": "2026-02-22 17:12:14",
    "close_time": "2026-02-22 19:17:25",
    "hold_hours": 2.1
  },
  {
    "id": "5f6730ec",
    "symbol": "ARC",
    "direction": "long",
    "entry_price": 0.08047,
    "exit_price": 0.08642,
    "tp_price": 0.091015,
    "sl_price": 0.08661350000000001,
    "position_value": 652.06,
    "pnl_pct": 7.39,
    "pnl_value": 23.62,
    "result": "win",
    "reason": "sl_hit",
    "signal_score": 73,
    "ml_confidence": 53.2,
    "ai_verdict": "Auto 做多 Score:73 ML:53%",
    "mtf_alignment": 0,
    "strategy_type": "trend",
    "open_time": "2026-02-22 17:12:14",
    "close_time": "2026-02-22 19:19:42",
    "hold_hours": 2.1
  },
  {
    "id": "7aae45f1",
    "symbol": "CYBER",
    "direction": "long",
    "entry_price": 0.6156,
    "exit_price": 0.5964,
    "tp_price": 0.692751,
    "sl_price": 0.623157,
    "position_value": 650.97,
    "pnl_pct": -3.12,
    "pnl_value": -20.3,
    "result": "loss",
    "reason": "sl_hit",
    "signal_score": 78,
    "ml_confidence": 40.1,
    "ai_verdict": "Auto 做多 Score:78 ML:40%",
    "mtf_alignment": 0,
    "strategy_type": "trend",
    "open_time": "2026-02-22 18:39:53",
    "close_time": "2026-02-22 19:39:56",
    "hold_hours": 1.0
  },
  {
    "id": "3156c7a1-partial-s1",
    "symbol": "PIPPIN",
    "direction": "long",
    "entry_price": 0.57754,
    "exit_price": 0.62392,
    "tp_price": 0.691644,
    "sl_price": 0.567004,
    "position_value": 220.66,
    "pnl_pct": 8.03,
    "pnl_value": 17.72,
    "result": "win",
    "reason": "partial_tp_s1",
    "signal_score": 77,
    "ml_confidence": 66.7,
    "ai_verdict": "Auto 做多 Score:77 ML:67%",
    "mtf_alignment": 0,
    "strategy_type": "grid",
    "open_time": "2026-02-22 17:12:14",
    "close_time": "2026-02-22 19:50:29",
    "hold_hours": 2.6
  },
  {
    "id": "3156c7a1",
    "symbol": "PIPPIN",
    "direction": "long",
    "entry_price": 0.57754,
    "exit_price": 0.61804,
    "tp_price": 0.691644,
    "sl_price": 0.6181018,
    "position_value": 735.52,
    "pnl_pct": 7.01,
    "pnl_value": 36.1,
    "result": "win",
    "reason": "sl_hit",
    "signal_score": 77,
    "ml_confidence": 66.7,
    "ai_verdict": "Auto 做多 Score:77 ML:67%",
    "mtf_alignment": 0,
    "strategy_type": "grid",
    "open_time": "2026-02-22 17:12:14",
    "close_time": "2026-02-22 21:13:19",
    "hold_hours": 4.0
  },
  {
    "id": "7d00e43b",
    "symbol": "ARC",
    "direction": "short",
    "entry_price": 0.09221,
    "exit_price": 0.09688,
    "tp_price": 0.078409,
    "sl_price": 0.0933929,
    "position_value": 1733.44,
    "pnl_pct": -5.06,
    "pnl_value": -87.79,
    "result": "loss",
    "reason": "sl_hit",
    "signal_score": 72,
    "ml_confidence": 42.1,
    "ai_verdict": "Auto 做空 Score:72 ML:42% 做空评分=60",
    "mtf_alignment": 0,
    "strategy_type": "trend",
    "open_time": "2026-02-22 21:16:14",
    "close_time": "2026-02-22 21:58:13",
    "hold_hours": 0.7
  },
  {
    "id": "b42eee9d-partial-s1",
    "symbol": "KITE",
    "direction": "long",
    "entry_price": 0.23841,
    "exit_price": 0.26448,
    "tp_price": 0.302254,
    "sl_price": 0.24093900000000001,
    "position_value": 195.67,
    "pnl_pct": 10.93,
    "pnl_value": 21.4,
    "result": "win",
    "reason": "partial_tp_s1",
    "signal_score": 73,
    "ml_confidence": 70.8,
    "ai_verdict": "Auto 做多 Score:73 ML:71%",
    "mtf_alignment": 0,
    "strategy_type": "trend",
    "open_time": "2026-02-22 17:12:14",
    "close_time": "2026-02-23 09:04:43",
    "hold_hours": 15.9
  },
  {
    "id": "c2034e43",
    "symbol": "RAVE",
    "direction": "long",
    "entry_price": 0.70968,
    "exit_price": 0.68589,
    "tp_price": 0.931982,
    "sl_price": 0.6906255,
    "position_value": 652.52,
    "pnl_pct": -3.35,
    "pnl_value": -21.87,
    "result": "loss",
    "reason": "sl_hit",
    "signal_score": 73,
    "ml_confidence": 68.4,
    "ai_verdict": "Auto 做多 Score:73 ML:68%",
    "mtf_alignment": 0,
    "strategy_type": "trend",
    "open_time": "2026-02-22 22:32:37",
    "close_time": "2026-02-23 09:07:03",
    "hold_hours": 10.6
  },
  {
    "id": "b42eee9d",
    "symbol": "KITE",
    "direction": "long",
    "entry_price": 0.23841,
    "exit_price": 0.25344,
    "tp_price": 0.302254,
    "sl_price": 0.2537913,
    "position_value": 652.23,
    "pnl_pct": 6.3,
    "pnl_value": 28.78,
    "result": "win",
    "reason": "sl_hit",
    "signal_score": 73,
    "ml_confidence": 70.8,
    "ai_verdict": "Auto 做多 Score:73 ML:71%",
    "mtf_alignment": 0,
    "strategy_type": "trend",
    "open_time": "2026-02-22 17:12:14",
    "close_time": "2026-02-23 10:27:22",
    "hold_hours": 17.3
  },
  {
    "id": "8ac632a5",
    "symbol": "RAVE",
    "direction": "long",
    "entry_price": 0.68361,
    "exit_price": 0.66838,
    "tp_price": 0.855597,
    "sl_price": 0.6688683000000001,
    "position_value": 648.19,
    "pnl_pct": -2.23,
    "pnl_value": -14.44,
    "result": "loss",
    "reason": "sl_hit",
    "signal_score": 73,
    "ml_confidence": 79.5,
    "ai_verdict": "Auto 做多 Score:73 ML:80%",
    "mtf_alignment": 0,
    "strategy_type": "trend",
    "open_time": "2026-02-23 09:11:37",
    "close_time": "2026-02-23 12:01:57",
    "hold_hours": 2.8
  },
  {
    "id": "7f89d6df",
    "symbol": "KITE",
    "direction": "long",
    "entry_price": 0.26069,
    "exit_price": 0.25556,
    "tp_price": 0.318688,
    "sl_price": 0.25571869999999997,
    "position_value": 731.31,
    "pnl_pct": -1.97,
    "pnl_value": -14.39,
    "result": "loss",
    "reason": "sl_hit",
    "signal_score": 73,
    "ml_confidence": 69.3,
    "ai_verdict": "Auto 做多 Score:73 ML:69%",
    "mtf_alignment": 0,
    "strategy_type": "grid",
    "open_time": "2026-02-23 12:04:45",
    "close_time": "2026-02-23 13:43:42",
    "hold_hours": 1.6
  },
  {
    "id": "668527a1",
    "symbol": "ENSO",
    "direction": "long",
    "entry_price": 2.0531,
    "exit_price": 2.0005,
    "tp_price": 2.644527,
    "sl_price": 2.0024063,
    "position_value": 649.98,
    "pnl_pct": -2.56,
    "pnl_value": -16.65,
    "result": "loss",
    "reason": "sl_hit",
    "signal_score": 74,
    "ml_confidence": 88.6,
    "ai_verdict": "Auto 做多 Score:74 ML:89%",
    "mtf_alignment": 0,
    "strategy_type": "trend",
    "open_time": "2026-02-23 12:04:45",
    "close_time": "2026-02-23 16:56:00",
    "hold_hours": 4.9
  },
  {
    "id": "4efcebb8-partial-s1",
    "symbol": "PIPPIN",
    "direction": "long",
    "entry_price": 0.66544,
    "exit_price": 0.72992,
    "tp_price": 0.8221,
    "sl_price": 0.6986844999999999,
    "position_value": 605.5,
    "pnl_pct": 9.69,
    "pnl_value": 58.67,
    "result": "win",
    "reason": "partial_tp_s1",
    "signal_score": 75,
    "ml_confidence": 83.4,
    "ai_verdict": "Auto 做多 Score:75 ML:83%",
    "mtf_alignment": 0,
    "strategy_type": "trend",
    "open_time": "2026-02-23 13:51:29",
    "close_time": "2026-02-23 18:12:05",
    "hold_hours": 4.3
  },
  {
    "id": "1b53c95e",
    "symbol": "KITE",
    "direction": "long",
    "entry_price": 0.25554,
    "exit_price": 0.25333,
    "tp_price": 0.315155,
    "sl_price": 0.253447,
    "position_value": 727.13,
    "pnl_pct": -0.86,
    "pnl_value": -6.29,
    "result": "loss",
    "reason": "sl_hit",
    "signal_score": 72,
    "ml_confidence": 74.5,
    "ai_verdict": "Auto 做多 Score:72 ML:74%",
    "mtf_alignment": 0,
    "strategy_type": "grid",
    "open_time": "2026-02-23 13:44:59",
    "close_time": "2026-02-23 18:50:08",
    "hold_hours": 5.1
  },
  {
    "id": "eaa7b197",
    "symbol": "KITE",
    "direction": "long",
    "entry_price": 0.25325,
    "exit_price": 0.24822,
    "tp_price": 0.311619,
    "sl_price": 0.24824689999999996,
    "position_value": 731.32,
    "pnl_pct": -1.99,
    "pnl_value": -14.53,
    "result": "loss",
    "reason": "sl_hit",
    "signal_score": 72,
    "ml_confidence": 80.2,
    "ai_verdict": "Auto 做多 Score:72 ML:80%",
    "mtf_alignment": 0,
    "strategy_type": "grid",
    "open_time": "2026-02-23 18:50:47",
    "close_time": "2026-02-23 20:35:24",
    "hold_hours": 1.7
  },
  {
    "id": "4efcebb8",
    "symbol": "PIPPIN",
    "direction": "long",
    "entry_price": 0.66544,
    "exit_price": 0.70306,
    "tp_price": 0.8221,
    "sl_price": 0.7041445,
    "position_value": 2018.35,
    "pnl_pct": 5.65,
    "pnl_value": 79.87,
    "result": "win",
    "reason": "sl_hit",
    "signal_score": 75,
    "ml_confidence": 83.4,
    "ai_verdict": "Auto 做多 Score:75 ML:83%",
    "mtf_alignment": 0,
    "strategy_type": "trend",
    "open_time": "2026-02-23 13:51:29",
    "close_time": "2026-02-23 21:29:52",
    "hold_hours": 7.6
  },
  {
    "id": "83e3cb2f",
    "symbol": "KITE",
    "direction": "long",
    "entry_price": 0.24763,
    "exit_price": 0.24031,
    "tp_price": 0.306549,
    "sl_price": 0.24257979999999998,
    "position_value": 730.52,
    "pnl_pct": -2.96,
    "pnl_value": -21.59,
    "result": "loss",
    "reason": "sl_hit",
    "signal_score": 73,
    "ml_confidence": 69.8,
    "ai_verdict": "Auto 做多 Score:73 ML:70%",
    "mtf_alignment": 0,
    "strategy_type": "grid",
    "open_time": "2026-02-23 20:36:07",
    "close_time": "2026-02-23 21:36:11",
    "hold_hours": 1.0
  },
  {
    "id": "b30f50b4",
    "symbol": "HNT",
    "direction": "long",
    "entry_price": 1.4007,
    "exit_price": 1.3811,
    "tp_price": 1.588927,
    "sl_price": 1.3845663000000001,
    "position_value": 973.76,
    "pnl_pct": -1.4,
    "pnl_value": -13.63,
    "result": "loss",
    "reason": "sl_hit",
    "signal_score": 72,
    "ml_confidence": 73.2,
    "ai_verdict": "Auto 做多 Score:72 ML:73%",
    "mtf_alignment": 0,
    "strategy_type": "trend",
    "open_time": "2026-02-24 07:49:01",
    "close_time": "2026-02-24 09:02:00",
    "hold_hours": 1.2
  },
  {
    "id": "ae868809",
    "symbol": "MON",
    "direction": "long",
    "entry_price": 0.02054,
    "exit_price": 0.02034,
    "tp_price": 0.022766,
    "sl_price": 0.020349199999999998,
    "position_value": 973.92,
    "pnl_pct": -0.97,
    "pnl_value": -9.48,
    "result": "loss",
    "reason": "sl_hit",
    "signal_score": 72,
    "ml_confidence": 80.0,
    "ai_verdict": "Auto 做多 Score:72 ML:80%",
    "mtf_alignment": 0,
    "strategy_type": "trend",
    "open_time": "2026-02-24 07:57:25",
    "close_time": "2026-02-24 09:11:22",
    "hold_hours": 1.2
  },
  {
    "id": "e702c9e7",
    "symbol": "MON",
    "direction": "long",
    "entry_price": 0.02079,
    "exit_price": 0.02045,
    "tp_price": 0.023128,
    "sl_price": 0.0205896,
    "position_value": 778.36,
    "pnl_pct": -1.64,
    "pnl_value": -12.73,
    "result": "loss",
    "reason": "sl_hit",
    "signal_score": 73,
    "ml_confidence": 84.7,
    "ai_verdict": "Auto 做多 Score:73 ML:85%",
    "mtf_alignment": 0,
    "strategy_type": "trend",
    "open_time": "2026-02-24 09:33:27",
    "close_time": "2026-02-24 10:33:31",
    "hold_hours": 1.0
  },
  {
    "id": "48be049b",
    "symbol": "KITE",
    "direction": "long",
    "entry_price": 0.24118,
    "exit_price": 0.23904,
    "tp_price": 0.302017,
    "sl_price": 0.23924800000000002,
    "position_value": 726.85,
    "pnl_pct": -0.89,
    "pnl_value": -6.45,
    "result": "loss",
    "reason": "sl_hit",
    "signal_score": 73,
    "ml_confidence": 66.4,
    "ai_verdict": "Auto 做多 Score:73 ML:66%",
    "mtf_alignment": 0,
    "strategy_type": "grid",
    "open_time": "2026-02-23 21:39:26",
    "close_time": "2026-02-24 11:18:35",
    "hold_hours": 13.7
  },
  {
    "id": "55518846",
    "symbol": "MY",
    "direction": "long",
    "entry_price": 0.122,
    "exit_price": 0.11014,
    "tp_price": 0.141299,
    "sl_price": 0.119406,
    "position_value": 3043.81,
    "pnl_pct": -9.72,
    "pnl_value": -295.9,
    "result": "loss",
    "reason": "sl_hit",
    "signal_score": 72,
    "ml_confidence": 86.9,
    "ai_verdict": "Auto 做多 Score:72 ML:87%",
    "mtf_alignment": 0,
    "strategy_type": "trend",
    "open_time": "2026-02-24 08:01:12",
    "close_time": "2026-02-24 19:43:00",
    "hold_hours": 11.7
  },
  {
    "id": "e10216c5-partial-s1",
    "symbol": "SIREN",
    "direction": "long",
    "entry_price": 0.27374,
    "exit_price": 0.31452,
    "tp_price": 0.369591,
    "sl_price": 0.283974,
    "position_value": 194.99,
    "pnl_pct": 14.9,
    "pnl_value": 29.05,
    "result": "win",
    "reason": "partial_tp_s1",
    "signal_score": 74,
    "ml_confidence": 92.3,
    "ai_verdict": "Auto 做多 Score:74 ML:92%",
    "mtf_alignment": 0,
    "strategy_type": "trend",
    "open_time": "2026-02-23 12:04:45",
    "close_time": "2026-02-24 22:09:31",
    "hold_hours": 34.1,
    "regime": "",
    "regime_at_entry": "",
    "fng_at_entry": 50,
    "btc_price_at_entry": 0,
    "peak_unrealized_pnl": 14.9,
    "initial_sl_price": 0.205275,
    "sl_distance_pct": 25.01
  },
  {
    "id": "397b789a-partial-s1",
    "symbol": "ENSO",
    "direction": "long",
    "entry_price": 2.3339,
    "exit_price": 2.5398,
    "tp_price": 2.83475,
    "sl_price": 2.3727,
    "position_value": 58.27,
    "pnl_pct": 8.82,
    "pnl_value": 5.14,
    "result": "win",
    "reason": "partial_tp_s1",
    "signal_score": 73,
    "ml_confidence": 52.2,
    "ai_verdict": "Auto 做多 Score:73 ML:52%",
    "mtf_alignment": 0,
    "strategy_type": "trend",
    "open_time": "2026-02-24 22:34:50",
    "close_time": "2026-02-24 22:49:16",
    "hold_hours": 0.2,
    "regime": "volatile",
    "regime_at_entry": "volatile",
    "fng_at_entry": 8,
    "btc_price_at_entry": 62829.2,
    "peak_unrealized_pnl": 8.82,
    "initial_sl_price": 1.97615,
    "sl_distance_pct": 15.33,
    "btc_macro_trend_at_entry": "bearish"
  },
  {
    "id": "e10216c5",
    "symbol": "SIREN",
    "direction": "long",
    "entry_price": 0.27374,
    "exit_price": 0.31934,
    "tp_price": 0.369591,
    "sl_price": 0.31940979999999997,
    "position_value": 649.98,
    "pnl_pct": 16.66,
    "pnl_value": 75.79,
    "result": "win",
    "reason": "sl_hit",
    "signal_score": 74,
    "ml_confidence": 92.3,
    "ai_verdict": "Auto 做多 Score:74 ML:92%",
    "mtf_alignment": 0,
    "strategy_type": "trend",
    "open_time": "2026-02-23 12:04:45",
    "close_time": "2026-02-24 23:01:51",
    "hold_hours": 35.0,
    "regime": "",
    "regime_at_entry": "",
    "fng_at_entry": 50,
    "btc_price_at_entry": 0,
    "decision_chain": {},
    "peak_unrealized_pnl": 23.69,
    "peak_unrealized_price": 0.33858,
    "initial_sl_price": 0.205275,
    "sl_distance_pct": 25.01,
    "btc_macro_trend_at_entry": ""
  },
  {
    "id": "397b789a-partial-s2",
    "symbol": "ENSO",
    "direction": "long",
    "entry_price": 2.3339,
    "exit_price": 2.691,
    "tp_price": 2.83475,
    "sl_price": 2.57553,
    "position_value": 40.79,
    "pnl_pct": 15.3,
    "pnl_value": 6.24,
    "result": "win",
    "reason": "partial_tp_s2",
    "signal_score": 73,
    "ml_confidence": 52.2,
    "ai_verdict": "Auto 做多 Score:73 ML:52%",
    "mtf_alignment": 0,
    "strategy_type": "trend",
    "open_time": "2026-02-24 22:34:50",
    "close_time": "2026-02-24 23:14:15",
    "hold_hours": 0.7,
    "regime": "volatile",
    "regime_at_entry": "volatile",
    "fng_at_entry": 8,
    "btc_price_at_entry": 62829.2,
    "peak_unrealized_pnl": 15.3,
    "initial_sl_price": 1.97615,
    "sl_distance_pct": 15.33,
    "btc_macro_trend_at_entry": "bearish"
  },
  {
    "id": "397b789a",
    "symbol": "ENSO",
    "direction": "long",
    "entry_price": 2.3339,
    "exit_price": 2.5711,
    "tp_price": 2.83475,
    "sl_price": 2.66085,
    "position_value": 194.24,
    "pnl_pct": 10.16,
    "pnl_value": 9.67,
    "result": "win",
    "reason": "sl_hit",
    "signal_score": 73,
    "ml_confidence": 52.2,
    "ai_verdict": "Auto 做多 Score:73 ML:52%",
    "mtf_alignment": 0,
    "strategy_type": "trend",
    "open_time": "2026-02-24 22:34:50",
    "close_time": "2026-02-24 23:35:00",
    "hold_hours": 1.0,
    "regime": "volatile",
    "regime_at_entry": "volatile",
    "fng_at_entry": 8,
    "btc_price_at_entry": 62829.2,
    "decision_chain": {
      "signal_score": 73,
      "ml_confidence": 52.2,
      "ml_label": "看涨",
      "strategy": "trend",
      "regime": "volatile",
      "fng": 8,
      "gate_passed": true,
      "sizing_amount": 194.24,
      "tp_mult": 3.5,
      "sl_mult": 2.5,
      "btc_macro_trend": "bearish",
      "btc_macro_filter": "bearish_long_reduced",
      "ml_paradox_check": "passed",
      "ml_paradox_reason": ""
    },
    "peak_unrealized_pnl": 17.07,
    "peak_unrealized_price": 2.7324,
    "initial_sl_price": 1.97615,
    "sl_distance_pct": 15.33,
    "btc_macro_trend_at_entry": "bearish"
  },
  {
    "id": "a2b577be-partial-s1",
    "symbol": "WLD",
    "direction": "long",
    "entry_price": 0.3775,
    "exit_price": 0.3921,
    "tp_price": 0.413925,
    "sl_price": 0.381193,
    "position_value": 58.38,
    "pnl_pct": 3.87,
    "pnl_value": 2.26,
    "result": "win",
    "reason": "partial_tp_s1",
    "signal_score": 72,
    "ml_confidence": 64.5,
    "ai_verdict": "Auto 做多 Score:72 ML:64%",
    "mtf_alignment": 0,
    "strategy_type": "trend",
    "open_time": "2026-02-24 22:56:46",
    "close_time": "2026-02-25 10:21:30",
    "hold_hours": 11.4,
    "regime": "volatile",
    "regime_at_entry": "volatile",
    "fng_at_entry": 8,
    "btc_price_at_entry": 63687.5,
    "peak_unrealized_pnl": 3.87,
    "initial_sl_price": 0.351483,
    "sl_distance_pct": 6.89,
    "btc_macro_trend_at_entry": "bearish"
  },
  {
    "id": "da34deab",
    "symbol": "CAKE",
    "direction": "long",
    "entry_price": 1.244,
    "exit_price": 1.2335,
    "tp_price": 1.346851,
    "sl_price": 1.2351842,
    "position_value": 809.95,
    "pnl_pct": -0.84,
    "pnl_value": -6.84,
    "result": "loss",
    "reason": "sl_hit",
    "signal_score": 72,
    "ml_confidence": 95.0,
    "ai_verdict": "Auto 做多 Score:72 ML:95%",
    "mtf_alignment": 0,
    "strategy_type": "trend",
    "open_time": "2026-02-25 10:13:04",
    "close_time": "2026-02-25 11:16:52",
    "hold_hours": 1.1,
    "regime": "volatile",
    "regime_at_entry": "volatile",
    "fng_at_entry": 11,
    "btc_price_at_entry": 66078.2,
    "decision_chain": {
      "signal_score": 72,
      "ml_confidence": 95.0,
      "ml_label": "看跌",
      "strategy": "trend",
      "regime": "volatile",
      "fng": 11,
      "gate_passed": true,
      "sizing_amount": 809.95,
      "tp_mult": 3.5,
      "sl_mult": 2.5,
      "btc_macro_trend": "bullish",
      "btc_macro_filter": "none",
      "ml_paradox_check": "size_reduced",
      "ml_paradox_reason": "ML=95>75做多+FNG=11<15"
    },
    "peak_unrealized_pnl": 0.23,
    "peak_unrealized_price": 1.2469,
    "initial_sl_price": 1.170535,
    "sl_distance_pct": 5.91,
    "btc_macro_trend_at_entry": "bullish"
  },
  {
    "id": "ded631a7",
    "symbol": "MNT",
    "direction": "long",
    "entry_price": 0.601,
    "exit_price": 0.5965,
    "tp_price": 0.6325,
    "sl_price": 0.5982999999999999,
    "position_value": 810.39,
    "pnl_pct": -0.75,
    "pnl_value": -6.07,
    "result": "loss",
    "reason": "sl_hit",
    "signal_score": 72,
    "ml_confidence": 89.5,
    "ai_verdict": "Auto 做多 Score:72 ML:90%",
    "mtf_alignment": 0,
    "strategy_type": "trend",
    "open_time": "2026-02-25 10:43:49",
    "close_time": "2026-02-25 11:43:49",
    "hold_hours": 1.0,
    "regime": "volatile",
    "regime_at_entry": "volatile",
    "fng_at_entry": 11,
    "btc_price_at_entry": 65906.0,
    "decision_chain": {
      "signal_score": 72,
      "ml_confidence": 89.5,
      "ml_label": "看跌",
      "strategy": "trend",
      "regime": "volatile",
      "fng": 11,
      "gate_passed": true,
      "sizing_amount": 810.39,
      "tp_mult": 3.5,
      "sl_mult": 2.5,
      "btc_macro_trend": "bullish",
      "btc_macro_filter": "none",
      "ml_paradox_check": "size_reduced",
      "ml_paradox_reason": "ML=90>75做多+FNG=11<15"
    },
    "peak_unrealized_pnl": 0.05,
    "peak_unrealized_price": 0.6013,
    "initial_sl_price": 0.5785,
    "sl_distance_pct": 3.74,
    "btc_macro_trend_at_entry": "bullish"
  },
  {
    "id": "a2b577be-partial-s2",
    "symbol": "WLD",
    "direction": "long",
    "entry_price": 0.3775,
    "exit_price": 0.4104,
    "tp_price": 0.413925,
    "sl_price": 0.382693,
    "position_value": 40.86,
    "pnl_pct": 8.72,
    "pnl_value": 3.56,
    "result": "win",
    "reason": "partial_tp_s2",
    "signal_score": 72,
    "ml_confidence": 64.5,
    "ai_verdict": "Auto 做多 Score:72 ML:64%",
    "mtf_alignment": 0,
    "strategy_type": "trend",
    "open_time": "2026-02-24 22:56:46",
    "close_time": "2026-02-26 10:47:48",
    "hold_hours": 35.9,
    "regime": "volatile",
    "regime_at_entry": "volatile",
    "fng_at_entry": 8,
    "btc_price_at_entry": 63687.5,
    "peak_unrealized_pnl": 8.72,
    "initial_sl_price": 0.351483,
    "sl_distance_pct": 6.89,
    "btc_macro_trend_at_entry": "bearish"
  },
  {
    "id": "a2b577be",
    "symbol": "WLD",
    "direction": "long",
    "entry_price": 0.3775,
    "exit_price": 0.4041,
    "tp_price": 0.413925,
    "sl_price": 0.4069965,
    "position_value": 194.59,
    "pnl_pct": 7.05,
    "pnl_value": 6.72,
    "result": "win",
    "reason": "sl_hit",
    "signal_score": 72,
    "ml_confidence": 64.5,
    "ai_verdict": "Auto 做多 Score:72 ML:64%",
    "mtf_alignment": 0,
    "strategy_type": "trend",
    "open_time": "2026-02-24 22:56:46",
    "close_time": "2026-02-26 21:18:46",
    "hold_hours": 46.4,
    "regime": "volatile",
    "regime_at_entry": "volatile",
    "fng_at_entry": 8,
    "btc_price_at_entry": 63687.5,
    "decision_chain": {
      "signal_score": 72,
      "ml_confidence": 64.5,
      "ml_label": "看跌",
      "strategy": "trend",
      "regime": "volatile",
      "fng": 8,
      "gate_passed": true,
      "sizing_amount": 194.59,
      "tp_mult": 3.5,
      "sl_mult": 2.5,
      "btc_macro_trend": "bearish",
      "btc_macro_filter": "bearish_long_reduced",
      "ml_paradox_check": "passed",
      "ml_paradox_reason": ""
    },
    "peak_unrealized_pnl": 9.19,
    "peak_unrealized_price": 0.4122,
    "initial_sl_price": 0.351483,
    "sl_distance_pct": 6.89,
    "btc_macro_trend_at_entry": "bearish"
  }
]